wechaty_meme_bot/__init__.py
wechaty_meme_bot/main.py
wechaty_meme_bot/meme_bot.py
wechaty_meme_bot-0.0.1.dist-info/METADATA
wechaty_meme_bot-0.0.1.dist-info/WHEEL
wechaty_meme_bot-0.0.1.dist-info/top_level.txt
wechaty_meme_bot-0.0.1.dist-info/RECORD
