Metadata-Version: 2.1
Name: wechaty-meme-bot
Version: 0.0.1
Summary: Wechaty-Meme-Bot is an interactive meme bot who respond interesting picture according to what he sees.
Home-page: https://github.com/MrZilinXiao/python-wechaty-meme-bot
Author: MrZilinXiao
Author-email: me@mrxiao.net
License: Apache-2.0
Project-URL: Bug Reports, https://github.com/MrZilinXiao/python-wechaty-meme-bot/issues
Project-URL: Source, https://github.com/MrZilinXiao/python-wechaty-meme-bot
Platform: UNKNOWN
Classifier: Programming Language :: Python :: 3.7
Classifier: License :: OSI Approved :: Apache Software License
Classifier: Operating System :: OS Independent
Requires-Dist: wechaty
Requires-Dist: Pillow
Requires-Dist: requests
